{
  "date": "2025-07-12",
  "retrieved_at": "2026-02-10T16:12:54.959307",
  "games": [
    {
      "event_id": "8ae9cdc6b767bfeb4f00b6c249520078",
      "commence_time": "2025-07-12T23:36:00Z",
      "home_team": "Houston Astros",
      "away_team": "Texas Rangers",
      "snapshot": "2025-07-12T22:36:00Z",
      "bookmaker": "fanduel",
      "markets": {
        "h2h": {
          "home_odds": "-118",
          "away_odds": "+100"
        },
        "spreads": {
          "home_line": 1.5,
          "home_odds": "-215",
          "away_line": -1.5,
          "away_odds": "+176"
        },
        "totals": {
          "line": 6.5,
          "over_odds": "-102",
          "under_odds": "-120"
        }
      }
    },
    {
      "event_id": "3059bccb405e5d0307f1e6bf2ccd59b5",
      "commence_time": "2025-07-12T23:36:00Z",
      "home_team": "San Diego Padres",
      "away_team": "Philadelphia Phillies",
      "snapshot": "2025-07-12T22:36:00Z",
      "bookmaker": "fanduel",
      "markets": {
        "h2h": {
          "home_odds": "+144",
          "away_odds": "-172"
        },
        "spreads": {
          "home_line": 1.5,
          "home_odds": "-122",
          "away_line": -1.5,
          "away_odds": "+102"
        },
        "totals": {
          "line": 7.5,
          "over_odds": "-102",
          "under_odds": "-120"
        }
      }
    }
  ],
  "meta": {
    "markets": [
      "h2h",
      "spreads",
      "totals",
      "pitcher_strikeouts",
      "pitcher_outs",
      "batter_hits",
      "batter_total_bases",
      "batter_home_runs",
      "batter_rbis",
      "batter_runs_scored",
      "batter_strikeouts"
    ],
    "regions": "us",
    "bookmakers": null,
    "hist_snapshots": [
      "2025-07-12T15:00:00Z",
      "2025-07-12T19:00:00Z",
      "2025-07-12T23:59:59Z"
    ],
    "snapshot_offset_minutes": 60,
    "probe_markets": true,
    "probe_stats": {
      "probed_events": 2,
      "events_with_markets": 2
    }
  }
}