{
  "date": "2025-08-25",
  "retrieved_at": "2026-02-10T16:21:04.182449",
  "pitcher_props": {
    "tomoyuki sugano": {
      "strikeouts": {
        "line": 3.5,
        "over_odds": "-112",
        "under_odds": "-112",
        "_src": "oddsapi"
      },
      "outs": {
        "line": 15.5,
        "over_odds": "-120",
        "under_odds": "-110",
        "_src": "oddsapi"
      }
    },
    "brennan bernardino": {
      "strikeouts": {
        "line": 0.5,
        "over_odds": "-250",
        "under_odds": "+185",
        "_src": "oddsapi"
      }
    },
    "spencer strider": {
      "outs": {
        "line": 16.5,
        "over_odds": "-150",
        "under_odds": "+110",
        "_src": "oddsapi"
      },
      "strikeouts": {
        "line": 6.5,
        "over_odds": "+118",
        "under_odds": "-154",
        "_src": "oddsapi"
      }
    },
    "edward cabrera": {
      "outs": {
        "line": 17.5,
        "over_odds": "+110",
        "under_odds": "-150",
        "_src": "oddsapi"
      },
      "strikeouts": {
        "line": 5.5,
        "over_odds": "-114",
        "under_odds": "-114",
        "_src": "oddsapi"
      }
    },
    "tanner bibee": {
      "outs": {
        "line": 17.5,
        "over_odds": "-200",
        "under_odds": "+150",
        "_src": "oddsapi"
      },
      "strikeouts": {
        "line": 5.5,
        "over_odds": "-130",
        "under_odds": "+101",
        "_src": "oddsapi"
      }
    },
    "ian seymour": {
      "strikeouts": {
        "line": 3.5,
        "over_odds": "-156",
        "under_odds": "+120",
        "_src": "oddsapi"
      },
      "outs": {
        "line": 13.5,
        "over_odds": "-121",
        "under_odds": null,
        "_src": "oddsapi"
      }
    },
    "cam schlittler": {
      "outs": {
        "line": 16.5,
        "over_odds": "-112",
        "under_odds": "-120",
        "_src": "oddsapi"
      },
      "strikeouts": {
        "line": 5.5,
        "over_odds": "-124",
        "under_odds": "-104",
        "_src": "oddsapi"
      }
    },
    "brad lord": {
      "outs": {
        "line": 14.5,
        "over_odds": "-146",
        "under_odds": "+112",
        "_src": "oddsapi"
      },
      "strikeouts": {
        "line": 4.5,
        "over_odds": "+112",
        "under_odds": "-152",
        "_src": "oddsapi"
      }
    },
    "joe ryan": {
      "outs": {
        "line": 18.0,
        "over_odds": "-120",
        "under_odds": "-120",
        "_src": "oddsapi"
      },
      "strikeouts": {
        "line": 5.5,
        "over_odds": "+124",
        "under_odds": "-161",
        "_src": "oddsapi"
      }
    },
    "max scherzer": {
      "outs": {
        "line": 17.5,
        "over_odds": "-165",
        "under_odds": "+125",
        "_src": "oddsapi"
      },
      "strikeouts": {
        "line": 6.5,
        "over_odds": "+113",
        "under_odds": "-147",
        "_src": "oddsapi"
      }
    },
    "cristopher sanchez": {
      "outs": {
        "line": 18.5,
        "over_odds": "+135",
        "under_odds": "-175",
        "_src": "oddsapi"
      },
      "strikeouts": {
        "line": 5.5,
        "over_odds": "-149",
        "under_odds": "+115",
        "_src": "oddsapi"
      }
    },
    "kodai senga": {
      "outs": {
        "line": 15.0,
        "over_odds": "-115",
        "under_odds": "-125",
        "_src": "oddsapi"
      },
      "strikeouts": {
        "line": 5.5,
        "over_odds": "+124",
        "under_odds": "-161",
        "_src": "oddsapi"
      }
    },
    "noah cameron": {
      "outs": {
        "line": 16.5,
        "over_odds": "-125",
        "under_odds": "-115",
        "_src": "oddsapi"
      },
      "strikeouts": {
        "line": 4.5,
        "over_odds": "-114",
        "under_odds": "-114",
        "_src": "oddsapi"
      }
    },
    "shane smith": {
      "outs": {
        "line": 15.0,
        "over_odds": "-115",
        "under_odds": "-125",
        "_src": "oddsapi"
      },
      "strikeouts": {
        "line": 3.5,
        "over_odds": "-164",
        "under_odds": "+125",
        "_src": "oddsapi"
      }
    },
    "eduardo rodriguez": {
      "outs": {
        "line": 17.5,
        "over_odds": "-115",
        "under_odds": "-125",
        "_src": "oddsapi"
      },
      "strikeouts": {
        "line": 4.5,
        "over_odds": "-106",
        "under_odds": "-122",
        "_src": "oddsapi"
      }
    },
    "brandon woodruff": {
      "outs": {
        "line": 17.5,
        "over_odds": "-125",
        "under_odds": "-115",
        "_src": "oddsapi"
      },
      "strikeouts": {
        "line": 6.5,
        "over_odds": "+107",
        "under_odds": "-139",
        "_src": "oddsapi"
      }
    },
    "michael mcgreevy": {
      "outs": {
        "line": 17.5,
        "over_odds": "-145",
        "under_odds": "+105",
        "_src": "oddsapi"
      },
      "strikeouts": {
        "line": 4.5,
        "over_odds": "+120",
        "under_odds": "-156",
        "_src": "oddsapi"
      }
    },
    "johan oviedo": {
      "strikeouts": {
        "line": 4.5,
        "over_odds": "-115",
        "under_odds": "-112",
        "_src": "oddsapi"
      },
      "outs": {
        "line": 14.5,
        "over_odds": "-170",
        "under_odds": "+125",
        "_src": "oddsapi"
      }
    }
  },
  "meta": {
    "markets": [
      "h2h",
      "spreads",
      "totals",
      "pitcher_strikeouts",
      "pitcher_outs",
      "batter_hits",
      "batter_total_bases",
      "batter_home_runs",
      "batter_rbis",
      "batter_runs_scored",
      "batter_strikeouts"
    ],
    "regions": "us",
    "bookmakers": null,
    "hist_snapshots": [
      "2025-08-25T15:00:00Z",
      "2025-08-25T19:00:00Z",
      "2025-08-25T23:59:59Z"
    ],
    "snapshot_offset_minutes": 60,
    "probe_markets": true,
    "probe_stats": {
      "probed_events": 9,
      "events_with_markets": 9
    }
  }
}